README.txt
setup.py
pyDots/__init__.py
pyDots/datas.py
pyDots/lists.py
pyDots/nones.py
pyDots/objects.py
pyDots.egg-info/PKG-INFO
pyDots.egg-info/SOURCES.txt
pyDots.egg-info/dependency_links.txt
pyDots.egg-info/not-zip-safe
pyDots.egg-info/top_level.txt