Metadata-Version: 1.1
Name: pyDots
Version: 1.1.17017
Summary: Dot-access to Python dicts like Javascript
Home-page: https://github.com/klahnakoski/pyDots
Author: Kyle Lahnakoski
Author-email: kyle@lahnakoski.com
License: MPL 2.0
Platform: UNKNOWN
Classifier: Development Status :: 4 - Beta
Classifier: Topic :: Software Development :: Libraries
Classifier: Topic :: Software Development :: Libraries :: Python Modules
Classifier: License :: OSI Approved :: Mozilla Public License 2.0 (MPL 2.0)
